pybootstrapui/__init__.py
pybootstrapui/__main__.py
pybootstrapui/_main.py
pybootstrapui/context_types.py
pybootstrapui/mishmash.py
pybootstrapui/zeroconfig.py
pybootstrapui/addons/__init__.py
pybootstrapui/addons/downloaders.py
pybootstrapui/addons/with_spinner.py
pybootstrapui/components/__init__.py
pybootstrapui/components/audio.py
pybootstrapui/components/base.py
pybootstrapui/components/buttons.py
pybootstrapui/components/cards.py
pybootstrapui/components/choices.py
pybootstrapui/components/custom.py
pybootstrapui/components/file_uploads.py
pybootstrapui/components/forms.py
pybootstrapui/components/grid.py
pybootstrapui/components/images.py
pybootstrapui/components/inputs.py
pybootstrapui/components/layout.py
pybootstrapui/components/lists.py
pybootstrapui/components/markdown.py
pybootstrapui/components/modals.py
pybootstrapui/components/notifications.py
pybootstrapui/components/progress.py
pybootstrapui/components/selectors.py
pybootstrapui/components/sliders.py
pybootstrapui/components/tables.py
pybootstrapui/components/text.py
pybootstrapui/components/tooltips.py
pybootstrapui/components/videos.py
pybootstrapui/components/dynamics/__init__.py
pybootstrapui/components/dynamics/client_to_server.py
pybootstrapui/components/dynamics/constants.py
pybootstrapui/components/dynamics/queue.py
pybootstrapui/components/dynamics/queue_handler.py
pybootstrapui/components/dynamics/server.py
pybootstrapui/desktop/__init__.py
pybootstrapui/desktop/build.py
pybootstrapui/desktop/built.py
pybootstrapui/desktop/nw_runner.py
pybootstrapui/modifiers/__init__.py
pybootstrapui/modifiers/buttons.py
pybootstrapui/modifiers/enumlike.py
pybootstrapui/modifiers/mod.py
pybootstrapui/templates/__build_init.py
pybootstrapui/templates/__init__.py
pybootstrapui/templates/aero.html
pybootstrapui/templates/cerulean.html
pybootstrapui/templates/cosmo.html
pybootstrapui/templates/cyborg.html
pybootstrapui/templates/darkly.html
pybootstrapui/templates/default.html
pybootstrapui-1.1.1.dist-info/LICENSE
pybootstrapui-1.1.1.dist-info/METADATA
pybootstrapui-1.1.1.dist-info/WHEEL
pybootstrapui-1.1.1.dist-info/top_level.txt
pybootstrapui-1.1.1.dist-info/RECORD
