Metadata-Version: 2.2
Name: PyBootstrapUI
Version: 1.1.1
Summary: A Python library for building web interfaces with dynamic and desktop features.
Home-page: https://github.com/oject0r/pybootstrapui
Author: oject0r
Author-email: oject0r <hd076@protonmail.com>
Maintainer-email: oject0r <hd076@protonmail.com>
License: MIT License
Keywords: PyBootstrapUI,bootstrap,web,desktop,gui,nwjs,nwjs-python,pyinstaller,pyinstaller-nwjs,interface,ui,user-interface,dynamic,dynamic-ui,dynamic-user-interface,dynamic-interface,aiohttp
Classifier: Programming Language :: Python :: 3
Classifier: License :: OSI Approved :: MIT License
Classifier: Operating System :: OS Independent
Classifier: Intended Audience :: Developers
Classifier: Topic :: Software Development :: User Interfaces
Classifier: Development Status :: 4 - Beta
Requires-Python: >=3.10
License-File: LICENSE
Requires-Dist: aiohttp
Requires-Dist: aiofiles
Provides-Extra: all
Requires-Dist: aiofiles; extra == "all"
Requires-Dist: pygments; extra == "all"
Requires-Dist: pyinstaller; extra == "all"
Requires-Dist: markdown; extra == "all"
Requires-Dist: httpx; extra == "all"
Dynamic: author
Dynamic: home-page
Dynamic: requires-python
